filebrowser/__init__.py
filebrowser/actions.py
filebrowser/admin.py
filebrowser/base.py
filebrowser/compat.py
filebrowser/decorators.py
filebrowser/fields.py
filebrowser/forms.py
filebrowser/models.py
filebrowser/namers.py
filebrowser/settings.py
filebrowser/signals.py
filebrowser/sites.py
filebrowser/storage.py
filebrowser/utils.py
filebrowser/locale/az/LC_MESSAGES/django.mo
filebrowser/locale/az/LC_MESSAGES/django.po
filebrowser/locale/bg_BG/LC_MESSAGES/django.mo
filebrowser/locale/bg_BG/LC_MESSAGES/django.po
filebrowser/locale/cs/LC_MESSAGES/django.mo
filebrowser/locale/cs/LC_MESSAGES/django.po
filebrowser/locale/de/LC_MESSAGES/django.mo
filebrowser/locale/de/LC_MESSAGES/django.po
filebrowser/locale/en/LC_MESSAGES/django.mo
filebrowser/locale/en/LC_MESSAGES/django.po
filebrowser/locale/es/LC_MESSAGES/django.mo
filebrowser/locale/es/LC_MESSAGES/django.po
filebrowser/locale/fa/LC_MESSAGES/django.mo
filebrowser/locale/fa/LC_MESSAGES/django.po
filebrowser/locale/fr/LC_MESSAGES/django.mo
filebrowser/locale/fr/LC_MESSAGES/django.po
filebrowser/locale/is/LC_MESSAGES/django.mo
filebrowser/locale/is/LC_MESSAGES/django.po
filebrowser/locale/it/LC_MESSAGES/django.mo
filebrowser/locale/it/LC_MESSAGES/django.po
filebrowser/locale/ja/LC_MESSAGES/django.mo
filebrowser/locale/ja/LC_MESSAGES/django.po
filebrowser/locale/ja_JP/LC_MESSAGES/django.mo
filebrowser/locale/ja_JP/LC_MESSAGES/django.po
filebrowser/locale/mn/LC_MESSAGES/django.mo
filebrowser/locale/mn/LC_MESSAGES/django.po
filebrowser/locale/nb/LC_MESSAGES/django.mo
filebrowser/locale/nb/LC_MESSAGES/django.po
filebrowser/locale/nl/LC_MESSAGES/django.po
filebrowser/locale/pl_PL/LC_MESSAGES/django.mo
filebrowser/locale/pl_PL/LC_MESSAGES/django.po
filebrowser/locale/pt_BR/LC_MESSAGES/django.mo
filebrowser/locale/pt_BR/LC_MESSAGES/django.po
filebrowser/locale/ru_RU/LC_MESSAGES/django.mo
filebrowser/locale/ru_RU/LC_MESSAGES/django.po
filebrowser/locale/sk/LC_MESSAGES/django.mo
filebrowser/locale/sk/LC_MESSAGES/django.po
django_filebrowser_no_grappelli-4.0.2.dist-info/AUTHORS
django_filebrowser_no_grappelli-4.0.2.dist-info/LICENSE
django_filebrowser_no_grappelli-4.0.2.dist-info/METADATA
django_filebrowser_no_grappelli-4.0.2.dist-info/WHEEL
django_filebrowser_no_grappelli-4.0.2.dist-info/top_level.txt
django_filebrowser_no_grappelli-4.0.2.dist-info/RECORD
