Metadata-Version: 2.1
Name: django-filebrowser-no-grappelli
Version: 4.0.2
Summary: Media-Management no Grappelli
Home-page: https://github.com/smacker/django-filebrowser-no-grappelli
Download-URL: 
Author: Patrick Kranzlmueller, Axel Swoboda (vonautomatisch)
Author-email: office@vonautomatisch.at
Maintainer: Maxim Sukharev
Maintainer-email: max@smacker.ru
License: BSD
Classifier: Development Status :: 5 - Production/Stable
Classifier: Environment :: Web Environment
Classifier: Framework :: Django
Classifier: Intended Audience :: Developers
Classifier: License :: OSI Approved :: BSD License
Classifier: Operating System :: OS Independent
Classifier: Programming Language :: Python
Classifier: Programming Language :: Python :: 2
Classifier: Programming Language :: Python :: 2.7
Classifier: Programming Language :: Python :: 3
Classifier: Programming Language :: Python :: 3.4
Classifier: Programming Language :: Python :: 3.5
Classifier: Programming Language :: Python :: 3.6
Classifier: Programming Language :: Python :: 3.7
Classifier: Programming Language :: Python :: 3.8
License-File: LICENSE
License-File: AUTHORS
